SeuPORT
